glinda/__init__.py
glinda/content.py
glinda/httpcompat.py
glinda/testing/__init__.py
glinda/testing/services.py
glinda-1.0.1.dist-info/LICENSE
glinda-1.0.1.dist-info/METADATA
glinda-1.0.1.dist-info/WHEEL
glinda-1.0.1.dist-info/top_level.txt
glinda-1.0.1.dist-info/zip-safe
glinda-1.0.1.dist-info/RECORD
