Metadata-Version: 2.1
Name: glinda
Version: 1.0.1
Summary: Helping your through the Tornado.
Home-page: http://github.com/dave-shawley/glinda
Author: Dave Shawley
Author-email: daveshawley@gmail.com
License: UNKNOWN
Platform: any
Classifier: Intended Audience :: Developers
Classifier: License :: OSI Approved :: BSD License
Classifier: Operating System :: OS Independent
Classifier: Programming Language :: Python
Classifier: Programming Language :: Python :: 2.7
Classifier: Programming Language :: Python :: 3.5
Classifier: Programming Language :: Python :: 3.6
Classifier: Programming Language :: Python :: 3.7
Classifier: Programming Language :: Python :: Implementation :: CPython
Classifier: Programming Language :: Python :: Implementation :: PyPy
Classifier: Development Status :: 5 - Production/Stable
Requires-Dist: ietfparse (<2,>=1.2.2)
Requires-Dist: tornado (<6.5,>=4.5)
